<annotation verified="yes">
    <folder>Annotation</folder>
    <filename>163.jpg</filename>
    <path>xpert-real--PascalVOC-export/Annotations/163.jpg</path>
    <source>
        <database>Unknown</database>
    </source>
    <size>
        <width>2041</width>
        <height>940</height>
        <depth>3</depth>
    </size>
    <segmented>0</segmented>
    <object>
    <name>cavity</name>
    <pose>Unspecified</pose>
    <truncated>0</truncated>
    <difficult>0</difficult>
    <bndbox>
        <xmin>1240.6679238459722</xmin>
        <ymin>592.1664969450102</ymin>
        <xmax>1255.9706417466282</xmax>
        <ymax>607.4822376507606</ymax>
    </bndbox>
</object><object>
    <name>cavity</name>
    <pose>Unspecified</pose>
    <truncated>0</truncated>
    <difficult>0</difficult>
    <bndbox>
        <xmin>786.1771321462044</xmin>
        <ymin>567.6614286651921</ymin>
        <xmax>799.9496016068892</xmax>
        <ymax>582.9771109462512</ymax>
    </bndbox>
</object>
</annotation>
