<annotation verified="yes">
    <folder>Annotation</folder>
    <filename>437.jpg</filename>
    <path>xpert-real--PascalVOC-export/Annotations/437.jpg</path>
    <source>
        <database>Unknown</database>
    </source>
    <size>
        <width>2041</width>
        <height>940</height>
        <depth>3</depth>
    </size>
    <segmented>0</segmented>
    <object>
    <name>cavity</name>
    <pose>Unspecified</pose>
    <truncated>0</truncated>
    <difficult>0</difficult>
    <bndbox>
        <xmin>920.8410963721665</xmin>
        <ymin>489.55141397697616</ymin>
        <xmax>920.8410963721665</xmax>
        <ymax>489.55141397697616</ymax>
    </bndbox>
</object>
</annotation>
